celery_serverless/__init__.py
celery_serverless/cli.py
celery_serverless/cli_utils.py
celery_serverless/deployer.py
celery_serverless/handler.py
celery_serverless/invoker.py
celery_serverless/worker_management.py
celery_serverless-0.2.0.dist-info/METADATA
celery_serverless-0.2.0.dist-info/RECORD
celery_serverless-0.2.0.dist-info/WHEEL
celery_serverless-0.2.0.dist-info/entry_points.txt
celery_serverless-0.2.0.dist-info/top_level.txt
