Metadata-Version: 2.1
Name: celery-serverless
Version: 0.2.0
Summary: Celery worker deployed as a Serverless application
Home-page: https://github.com/alanjds/celery-serverless
Author: Alan Justino & Samuel Barbosa Neto
Author-email: alan.justino@yahoo.com.br
License: Apache Software License 2.0
Keywords: celery_serverless
Platform: UNKNOWN
Classifier: Development Status :: 2 - Pre-Alpha
Classifier: Intended Audience :: Developers
Classifier: License :: OSI Approved :: Apache Software License
Classifier: Natural Language :: English
Classifier: Programming Language :: Python :: 3
Classifier: Programming Language :: Python :: 3.5
Classifier: Programming Language :: Python :: 3.6
Requires-Dist: Click (>=6.0)
Requires-Dist: celery (~=4.1.0)
Requires-Dist: ruamel.yaml (~=0.15.37)
